layered_bias_probe/__init__.py
layered_bias_probe/cli.py
layered_bias_probe/config/__init__.py
layered_bias_probe/config/default.yaml
layered_bias_probe/core/__init__.py
layered_bias_probe/core/batch_processor.py
layered_bias_probe/core/bias_probe.py
layered_bias_probe/core/fine_tuner.py
layered_bias_probe/core/results_analyzer.py
layered_bias_probe/utils/__init__.py
layered_bias_probe/utils/bias_quantifier.py
layered_bias_probe/utils/embedding_extractor.py
layered_bias_probe/utils/model_manager.py
layered_bias_probe/utils/weat_category.py
layered_bias_probe/utils/weathub_loader.py
layered_bias_probe-1.0.1.dist-info/licenses/LICENSE
layered_bias_probe-1.0.1.dist-info/METADATA
layered_bias_probe-1.0.1.dist-info/WHEEL
layered_bias_probe-1.0.1.dist-info/entry_points.txt
layered_bias_probe-1.0.1.dist-info/top_level.txt
layered_bias_probe-1.0.1.dist-info/RECORD
