Metadata-Version: 2.4
Name: layered-bias-probe
Version: 1.0.1
Summary: A comprehensive toolkit for layer-wise bias analysis in language models with fine-tuning support
Home-page: https://github.com/DevDaring/layered-bias-probe
Author: DebK
Author-email: koushikdeb88@gmail.com
Project-URL: Bug Reports, https://github.com/DevDaring/layered-bias-probe/issues
Project-URL: Source, https://github.com/DevDaring/layered-bias-probe
Project-URL: Documentation, https://github.com/DevDaring/layered-bias-probe#readme
Project-URL: Homepage, https://github.com/DevDaring/layered-bias-probe
Keywords: bias nlp language-models weat fairness transformers machine-learning layer-analysis fine-tuning
Classifier: Development Status :: 4 - Beta
Classifier: Intended Audience :: Developers
Classifier: Intended Audience :: Science/Research
Classifier: Topic :: Scientific/Engineering :: Artificial Intelligence
Classifier: Topic :: Software Development :: Libraries :: Python Modules
Classifier: License :: OSI Approved :: MIT License
Classifier: Operating System :: OS Independent
Classifier: Programming Language :: Python :: 3
Classifier: Programming Language :: Python :: 3.8
Classifier: Programming Language :: Python :: 3.9
Classifier: Programming Language :: Python :: 3.10
Classifier: Programming Language :: Python :: 3.11
Requires-Python: >=3.8
License-File: LICENSE
Requires-Dist: torch>=2.0.0
Requires-Dist: transformers>=4.32.0
Requires-Dist: datasets>=2.0.0
Requires-Dist: pandas>=1.5.0
Requires-Dist: numpy>=1.21.0
Requires-Dist: scikit-learn>=1.1.0
Requires-Dist: tqdm>=4.64.0
Requires-Dist: accelerate>=0.20.0
Requires-Dist: bitsandbytes>=0.40.0
Requires-Dist: huggingface_hub>=0.16.0
Requires-Dist: plotly>=5.0.0
Requires-Dist: matplotlib>=3.5.0
Requires-Dist: seaborn>=0.11.0
Requires-Dist: pyyaml>=6.0
Requires-Dist: click>=8.0.0
Requires-Dist: kaleido>=0.1.0
Dynamic: author
Dynamic: author-email
Dynamic: classifier
Dynamic: description
Dynamic: description-content-type
Dynamic: home-page
Dynamic: keywords
Dynamic: license-file
Dynamic: project-url
Dynamic: requires-dist
Dynamic: requires-python
Dynamic: summary
